{
  "$schema": "http://schema.management.azure.com/schemas/2015-01-01/deploymentParameters.json#",
  "contentVersion": "1.0.0.0",
  "parameters": {
    "input": {
      "value": {
        "Id": "/providers/Microsoft.Management/managementGroups/man-landingzones",
        "Type": "/providers/Microsoft.Management/managementGroups",
        "Name": "man-landingzones",
        "TenantId": "d6ad82f3-42af-4a15-ac1e-49e6c08f624e",
        "DisplayName": "man-landingzones",
        "UpdatedTime": "0001-01-01T00:00:00Z",
        "UpdatedBy": null,
        "ParentId": "/providers/Microsoft.Management/managementGroups/man",
        "ParentName": "man",
        "ParentDisplayName": "man",
        "Children": [
          {
            "Type": "/providers/Microsoft.Management/managementGroups",
            "Id": "/providers/Microsoft.Management/managementGroups/man-corp",
            "Name": "man-corp",
            "DisplayName": "man-corp",
            "Children": null
          },
          {
            "Type": "/providers/Microsoft.Management/managementGroups",
            "Id": "/providers/Microsoft.Management/managementGroups/man-online",
            "Name": "man-online",
            "DisplayName": "man-online",
            "Children": null
          },
          {
            "Type": "/providers/Microsoft.Management/managementGroups",
            "Id": "/providers/Microsoft.Management/managementGroups/man-sap",
            "Name": "man-sap",
            "DisplayName": "man-sap",
            "Children": null
          }
        ],
        "properties": {
          "policyDefinitions": [],
          "policySetDefinitions": [],
          "policyAssignments": [
            {
              "Identity": null,
              "Location": "westeurope",
              "Name": "Deny-IP-forwarding",
              "PolicyAssignmentId": "/providers/Microsoft.Management/managementGroups/man-landingzones/providers/Microsoft.Authorization/policyAssignments/Deny-IP-forwarding",
              "Properties": {
                "Description": "Deny-IP-Forwarding",
                "DisplayName": "Deny-IP-Forwarding",
                "NotScopes": null,
                "Parameters": null,
                "PolicyDefinitionId": "/providers/Microsoft.Authorization/policyDefinitions/88c0b9da-ce96-4b03-9635-f29a937e2900",
                "Scope": "/providers/Microsoft.Management/managementGroups/man-landingzones"
              },
              "ResourceGroupName": null,
              "ResourceId": "/providers/Microsoft.Management/managementGroups/man-landingzones/providers/Microsoft.Authorization/policyAssignments/Deny-IP-forwarding",
              "ResourceName": "Deny-IP-forwarding",
              "ResourceType": "Microsoft.Authorization/policyAssignments",
              "Sku": {
                "name": "A0",
                "tier": "Free"
              },
              "SubscriptionId": null
            },
            {
              "Identity": null,
              "Location": "westeurope",
              "Name": "Deny-Storage-http",
              "PolicyAssignmentId": "/providers/Microsoft.Management/managementGroups/man-landingzones/providers/Microsoft.Authorization/policyAssignments/Deny-Storage-http",
              "Properties": {
                "Description": "Enforce-Secure-Storage",
                "DisplayName": "Enforce-Secure-Storage",
                "NotScopes": null,
                "Parameters": null,
                "PolicyDefinitionId": "/providers/Microsoft.Authorization/policyDefinitions/404c3081-a854-4457-ae30-26a93ef643f9",
                "Scope": "/providers/Microsoft.Management/managementGroups/man-landingzones"
              },
              "ResourceGroupName": null,
              "ResourceId": "/providers/Microsoft.Management/managementGroups/man-landingzones/providers/Microsoft.Authorization/policyAssignments/Deny-Storage-http",
              "ResourceName": "Deny-Storage-http",
              "ResourceType": "Microsoft.Authorization/policyAssignments",
              "Sku": {
                "name": "A0",
                "tier": "Free"
              },
              "SubscriptionId": null
            },
            {
              "Identity": null,
              "Location": "westeurope",
              "Name": "Deny-Subnet-Without-Nsg",
              "PolicyAssignmentId": "/providers/Microsoft.Management/managementGroups/man-landingzones/providers/Microsoft.Authorization/policyAssignments/Deny-Subnet-Without-Nsg",
              "Properties": {
                "Description": "Deny-Subnet-Without-Nsg",
                "DisplayName": "Deny-Subnet-Without-Nsg",
                "NotScopes": null,
                "Parameters": null,
                "PolicyDefinitionId": "/providers/Microsoft.Management/managementGroups/man/providers/Microsoft.Authorization/policyDefinitions/Deny-Subnet-Without-Nsg",
                "Scope": "/providers/Microsoft.Management/managementGroups/man-landingzones"
              },
              "ResourceGroupName": null,
              "ResourceId": "/providers/Microsoft.Management/managementGroups/man-landingzones/providers/Microsoft.Authorization/policyAssignments/Deny-Subnet-Without-Nsg",
              "ResourceName": "Deny-Subnet-Without-Nsg",
              "ResourceType": "Microsoft.Authorization/policyAssignments",
              "Sku": {
                "name": "A0",
                "tier": "Free"
              },
              "SubscriptionId": null
            },
            {
              "Identity": {
                "principalId": "bcf3bc19-df23-4ea3-8cdb-86a5f345d199",
                "tenantId": "d6ad82f3-42af-4a15-ac1e-49e6c08f624e",
                "type": "SystemAssigned"
              },
              "Location": "westeurope",
              "Name": "Deploy-VM-Backup",
              "PolicyAssignmentId": "/providers/Microsoft.Management/managementGroups/man-landingzones/providers/Microsoft.Authorization/policyAssignments/Deploy-VM-Backup",
              "Properties": {
                "Description": "Deploy-VM-Backup",
                "DisplayName": "Deploy-VM-Backup",
                "NotScopes": null,
                "Parameters": {},
                "PolicyDefinitionId": "/providers/Microsoft.Management/managementGroups/man/providers/Microsoft.Authorization/policyDefinitions/Deploy-AzureBackup-on-VM",
                "Scope": "/providers/Microsoft.Management/managementGroups/man-landingzones"
              },
              "ResourceGroupName": null,
              "ResourceId": "/providers/Microsoft.Management/managementGroups/man-landingzones/providers/Microsoft.Authorization/policyAssignments/Deploy-VM-Backup",
              "ResourceName": "Deploy-VM-Backup",
              "ResourceType": "Microsoft.Authorization/policyAssignments",
              "Sku": {
                "name": "A0",
                "tier": "Free"
              },
              "SubscriptionId": null
            },
            {
              "Identity": {
                "principalId": "8ec75701-f193-4a6e-a320-00103809f222",
                "tenantId": "d6ad82f3-42af-4a15-ac1e-49e6c08f624e",
                "type": "SystemAssigned"
              },
              "Location": "westeurope",
              "Name": "Enforce-SQL-Encryption",
              "PolicyAssignmentId": "/providers/Microsoft.Management/managementGroups/man-landingzones/providers/Microsoft.Authorization/policyAssignments/Enforce-SQL-Encryption",
              "Properties": {
                "Description": "Deploy-SQL-Security",
                "DisplayName": "Deploy-SQL-Security",
                "NotScopes": null,
                "Parameters": null,
                "PolicyDefinitionId": "/providers/Microsoft.Authorization/policyDefinitions/86a912f6-9a06-4e26-b447-11b16ba8659f",
                "Scope": "/providers/Microsoft.Management/managementGroups/man-landingzones"
              },
              "ResourceGroupName": null,
              "ResourceId": "/providers/Microsoft.Management/managementGroups/man-landingzones/providers/Microsoft.Authorization/policyAssignments/Enforce-SQL-Encryption",
              "ResourceName": "Enforce-SQL-Encryption",
              "ResourceType": "Microsoft.Authorization/policyAssignments",
              "Sku": {
                "name": "A0",
                "tier": "Free"
              },
              "SubscriptionId": null
            }
          ],
          "roleDefinitions": null,
          "roleAssignments": null
        }
      }
    }
  }
}
