{
    "name": "DenyAction-DeleteProtection",
    "type": "Microsoft.Authorization/policySetDefinitions",
    "apiVersion": "2021-06-01",
    "scope": null,
    "properties": {
        "policyType": "Custom",
        "displayName": "DenyAction Delete - Activity Logs and Diagnostic Settings",
        "description": "Enforces DenyAction - Delete on Activity Logs and Diagnostic Settings.",
        "metadata": {
            "version": "1.0.0",
            "category": "Monitoring",
            "source": "https://github.com/Azure/Enterprise-Scale/",
            "alzCloudEnvironments": [
                "AzureCloud",
                "AzureChinaCloud",
                "AzureUSGovernment"
            ]
        },
        "parameters": {},
        "policyDefinitions": [
            {
                "policyDefinitionReferenceId": "SandboxNotAllowed",
                "policyDefinitionId": "/providers/Microsoft.Authorization/policyDefinitions/6c112d4e-5bc7-47ae-a041-ea2d9dccd749",
                "parameters": {
                    "effect": {
                        "value": "[[parameters('effectNotAllowedResources')]"
                      },
                    "listOfResourceTypesNotAllowed": {
                        "value": "[[parameters('listOfResourceTypesNotAllowed')]"
                    }
                },
                "groupNames": []
            },
            {
                "policyDefinitionReferenceId": "SandboxDenyVnetPeering",
                "policyDefinitionId": "/providers/Microsoft.Management/managementGroups/contoso/providers/Microsoft.Authorization/policyDefinitions/Deny-VNET-Peer-Cross-Sub",
                "parameters": {
                    "effect": {
                        "value": "[[parameters('effectDenyVnetPeering')]"
                      }
                },
                "groupNames": []
            }
        ],
        "policyDefinitionGroups": null
    }
}