{
    "$schema": "https://schema.management.azure.com/schemas/2019-08-01/managementGroupDeploymentTemplate.json#",
    "contentVersion": "1.0.0.0",
    "parameters": {
        "enforcementMode": {
            "type": "string",
            "allowedValues": [
                "Default",
                "DoNotEnforce"
            ],
            "defaultValue": "Default"
        },
        "nonComplianceMessagePlaceholder": {
            "type": "string",
            "defaultValue": "{enforcementMode}"
        }
    },
    "variables": {
        "policyDefinitions": {
            "ascMonitoring": "/providers/Microsoft.Authorization/policySetDefinitions/1f3afdf9-d0c9-4c3d-847f-89da613e70a8"
        },
        "policyAssignmentNames": {
            "ascMonitoring": "Deploy-ASC-Monitoring",
            "description": "Microsoft Cloud Security Benchmark policy initiative.",
            "displayName": "Microsoft Cloud Security Benchmark"
        },
        "nonComplianceMessage": {
            "message": "Microsoft Cloud Security Benchmark {enforcementMode} be met.",
            "Default": "must",
            "DoNotEnforce": "should"
        }
      },
    "resources": [
        {
            "type": "Microsoft.Authorization/policyAssignments",
            "apiVersion": "2022-06-01",
            "name": "[variables('policyAssignmentNames').ascMonitoring]",
            "location": "[deployment().location]",
            "identity": {
                "type": "SystemAssigned"
            },
            "properties": {
                "description": "[variables('policyAssignmentNames').description]",
                "displayName": "[variables('policyAssignmentNames').displayName]",
                "policyDefinitionId": "[variables('policyDefinitions').ascMonitoring]",
                "enforcementMode": "[parameters('enforcementMode')]",
                "nonComplianceMessages": [
                    {
                        "message": "[replace(variables('nonComplianceMessage').message, parameters('nonComplianceMessagePlaceholder'), variables('nonComplianceMessage')[parameters('enforcementMode')])]"
                    }
                ],
                "parameters": {}
            }
        }
    ],
    "outputs": {}
}