{
  "$schema": "http://schema.management.azure.com/schemas/2015-01-01/deploymentParameters.json#",
  "contentVersion": "1.0.0.0",
  "parameters": {
    "input": {
      "value": {
        "Name": "Deny-PublicEndpoint-Sql",
        "ResourceId": "/providers/Microsoft.Management/managementGroups/rem/providers/Microsoft.Authorization/policyDefinitions/Deny-PublicEndpoint-Sql",
        "ResourceName": "Deny-PublicEndpoint-Sql",
        "ResourceType": "Microsoft.Authorization/policyDefinitions",
        "SubscriptionId": null,
        "PolicyDefinitionId": "/providers/Microsoft.Management/managementGroups/rem/providers/Microsoft.Authorization/policyDefinitions/Deny-PublicEndpoint-Sql",
        "Properties": {
          "Description": "This policy restrict creation of Sql servers with exposed public endpoints",
          "DisplayName": "Deny-PublicEndpoint-Sql",
          "Mode": "All",
          "Parameters": null,
          "PolicyRule": {
            "if": {
              "allOf": [
                {
                  "field": "type",
                  "equals": "Microsoft.Sql/servers"
                },
                {
                  "field": "Microsoft.Sql/servers/publicNetworkAccess",
                  "notequals": "Disabled"
                }
              ]
            },
            "then": {
              "effect": "Deny"
            }
          }
        }
      }
    }
  }
}
