{
  "$schema": "http://schema.management.azure.com/schemas/2015-01-01/deploymentParameters.json#",
  "contentVersion": "1.0.0.0",
  "parameters": {
    "input": {
      "value": {
        "Id": "/providers/Microsoft.Management/managementGroups/con-platform",
        "Type": "/providers/Microsoft.Management/managementGroups",
        "Name": "con-platform",
        "TenantId": "d6ad82f3-42af-4a15-ac1e-49e6c08f624e",
        "DisplayName": "con-platform",
        "UpdatedTime": "0001-01-01T00:00:00Z",
        "UpdatedBy": null,
        "ParentId": "/providers/Microsoft.Management/managementGroups/con",
        "ParentName": "con",
        "ParentDisplayName": "con",
        "Children": [
          {
            "Type": "/providers/Microsoft.Management/managementGroups",
            "Id": "/providers/Microsoft.Management/managementGroups/con-management",
            "Name": "con-management",
            "DisplayName": "con-management",
            "Children": null
          },
          {
            "Type": "/providers/Microsoft.Management/managementGroups",
            "Id": "/providers/Microsoft.Management/managementGroups/con-connectivity",
            "Name": "con-connectivity",
            "DisplayName": "con-connectivity",
            "Children": null
          },
          {
            "Type": "/providers/Microsoft.Management/managementGroups",
            "Id": "/providers/Microsoft.Management/managementGroups/con-identity",
            "Name": "con-identity",
            "DisplayName": "con-identity",
            "Children": null
          }
        ],
        "properties": {
          "policyDefinitions": [],
          "policySetDefinitions": [],
          "policyAssignments": [],
          "roleDefinitions": [],
          "roleAssignments": []
        }
      }
    }
  }
}
